prometheus_virtual_metrics/__init__.py
prometheus_virtual_metrics/__main__.py
prometheus_virtual_metrics/_version.py
prometheus_virtual_metrics/constants.py
prometheus_virtual_metrics/context.py
prometheus_virtual_metrics/default_settings.py
prometheus_virtual_metrics/exceptions.py
prometheus_virtual_metrics/promql.py
prometheus_virtual_metrics/pytest_plugin.py
prometheus_virtual_metrics/request.py
prometheus_virtual_metrics/response.py
prometheus_virtual_metrics/server.py
prometheus_virtual_metrics/django_app/__init__.py
prometheus_virtual_metrics/django_app/apps.py
prometheus_virtual_metrics/django_app/state.py
prometheus_virtual_metrics/django_app/views.py
prometheus_virtual_metrics/plugins/__init__.py
prometheus_virtual_metrics/plugins/_rlpython.py
prometheus_virtual_metrics/plugins/basic_auth.py
prometheus_virtual_metrics/plugins/catch_errors.py
prometheus_virtual_metrics/plugins/example.py
prometheus_virtual_metrics-0.4.0.dist-info/licenses/LICENSE.txt
prometheus_virtual_metrics-0.4.0.dist-info/METADATA
prometheus_virtual_metrics-0.4.0.dist-info/WHEEL
prometheus_virtual_metrics-0.4.0.dist-info/entry_points.txt
prometheus_virtual_metrics-0.4.0.dist-info/top_level.txt
prometheus_virtual_metrics-0.4.0.dist-info/RECORD
