Metadata-Version: 2.4
Name: prometheus-virtual-metrics
Version: 0.4.0
Author-email: Florian Scherf <mail@florianscherf.de>
License: MIT License
Project-URL: Homepage, https://pages.fscherf.de/prometheus-virtual-metrics/
Project-URL: Repository, https://github.com/fscherf/prometheus-virtual-metrics
Project-URL: Bug Tracker, https://github.com/fscherf/prometheus-virtual-metrics/issues
Classifier: Development Status :: 4 - Beta
Classifier: Intended Audience :: Developers
Classifier: Intended Audience :: System Administrators
Classifier: License :: OSI Approved :: MIT License
Classifier: Operating System :: Unix
Classifier: Framework :: AsyncIO
Requires-Python: >=3.9
License-File: LICENSE.txt
Requires-Dist: aiohttp<4,>=3.9
Requires-Dist: simple-logging-setup
Requires-Dist: promql-parser
Requires-Dist: rlpython
Provides-Extra: dev
Requires-Dist: watchfiles; extra == "dev"
Requires-Dist: rlpython; extra == "dev"
Provides-Extra: test
Requires-Dist: coverage==7.6.1; extra == "test"
Requires-Dist: pytest==8.3.3; extra == "test"
Requires-Dist: rlpython; extra == "test"
Requires-Dist: requests; extra == "test"
Requires-Dist: pytest-django==4.10.0; extra == "test"
Requires-Dist: django~=4.2; extra == "test"
Provides-Extra: doc
Requires-Dist: mkdocs==1.6.1; extra == "doc"
Requires-Dist: mkdocstrings[python]==0.28.2; extra == "doc"
Requires-Dist: mkdocs-material==9.6.6; extra == "doc"
Requires-Dist: grip==4.6.2; extra == "doc"
Dynamic: license-file
